{"data": {"CO": 1.207397260273973, "PM10": 131.42739726027398, "O3": 102.72328767123288, "SO2": 20.15890410958904, "NO2": 57.12876712328767, "AQI": 102.75068493150685, "PM25": 52.054794520547944}, "name": "year", "children": [{"data": {"CO": 0.8333333333333334, "PM10": 146.92222222222222, "O3": 121.24444444444444, "SO2": 12.28888888888889, "NO2": 51.44444444444444, "AQI": 110.42222222222222, "PM25": 53.94444444444444}, "name": "Q1", "children": [{"data": {"CO": 1.9000000000000006, "PM10": 208.0, "O3": 67.64516129032258, "SO2": 37.03225806451613, "NO2": 72.48387096774194, "AQI": 140.1290322580645, "PM25": 78.70967741935483}, "name": "Jan.", "children": [{"data": {"CO": 2.1, "PM10": 119.0, "O3": 50.0, "SO2": 42.0, "NO2": 75.0, "AQI": 94.0, "PM25": 66.0}, "name": "1, Jan."}, {"data": {"CO": 2.8, "PM10": 161.0, "O3": 46.0, "SO2": 45.0, "NO2": 94.0, "AQI": 129.0, "PM25": 98.0}, "name": "2, Jan."}, {"data": {"CO": 3.4, "PM10": 192.0, "O3": 52.0, "SO2": 56.0, "NO2": 113.0, "AQI": 152.0, "PM25": 116.0}, "name": "3, Jan."}, {"data": {"CO": 3.9, "PM10": 226.0, "O3": 56.0, "SO2": 60.0, "NO2": 137.0, "AQI": 202.0, "PM25": 152.0}, "name": "4, Jan."}, {"data": {"CO": 3.4, "PM10": 218.0, "O3": 63.0, "SO2": 49.0, "NO2": 123.0, "AQI": 189.0, "PM25": 142.0}, "name": "5, Jan."}, {"data": {"CO": 1.3, "PM10": 115.0, "O3": 58.0, "SO2": 33.0, "NO2": 63.0, "AQI": 83.0, "PM25": 53.0}, "name": "6, Jan."}, {"data": {"CO": 1.8, "PM10": 98.0, "O3": 64.0, "SO2": 31.0, "NO2": 76.0, "AQI": 95.0, "PM25": 52.0}, "name": "7, Jan."}, {"data": {"CO": 1.3, "PM10": 84.0, "O3": 69.0, "SO2": 30.0, "NO2": 57.0, "AQI": 72.0, "PM25": 46.0}, "name": "8, Jan."}, {"data": {"CO": 1.0, "PM10": 59.0, "O3": 74.0, "SO2": 28.0, "NO2": 46.0, "AQI": 58.0, "PM25": 34.0}, "name": "9, Jan."}, {"data": {"CO": 0.8, "PM10": 51.0, "O3": 70.0, "SO2": 21.0, "NO2": 36.0, "AQI": 51.0, "PM25": 28.0}, "name": "10, Jan."}, {"data": {"CO": 1.8, "PM10": 102.0, "O3": 46.0, "SO2": 33.0, "NO2": 72.0, "AQI": 90.0, "PM25": 60.0}, "name": "11, Jan."}, {"data": {"CO": 2.4, "PM10": 157.0, "O3": 58.0, "SO2": 37.0, "NO2": 92.0, "AQI": 129.0, "PM25": 98.0}, "name": "12, Jan."}, {"data": {"CO": 2.6, "PM10": 175.0, "O3": 57.0, "SO2": 41.0, "NO2": 96.0, "AQI": 138.0, "PM25": 105.0}, "name": "13, Jan."}, {"data": {"CO": 2.2, "PM10": 154.0, "O3": 65.0, "SO2": 46.0, "NO2": 83.0, "AQI": 120.0, "PM25": 91.0}, "name": "14, Jan."}, {"data": {"CO": 1.5, "PM10": 124.0, "O3": 80.0, "SO2": 36.0, "NO2": 65.0, "AQI": 87.0, "PM25": 56.0}, "name": "15, Jan."}, {"data": {"CO": 1.2, "PM10": 106.0, "O3": 73.0, "SO2": 32.0, "NO2": 56.0, "AQI": 78.0, "PM25": 42.0}, "name": "16, Jan."}, {"data": {"CO": 1.2, "PM10": 87.0, "O3": 66.0, "SO2": 30.0, "NO2": 52.0, "AQI": 69.0, "PM25": 44.0}, "name": "17, Jan."}, {"data": {"CO": 1.5, "PM10": 126.0, "O3": 74.0, "SO2": 35.0, "NO2": 61.0, "AQI": 88.0, "PM25": 63.0}, "name": "18, Jan."}, {"data": {"CO": 1.1, "PM10": 374.0, "O3": 88.0, "SO2": 22.0, "NO2": 50.0, "AQI": 235.0, "PM25": 78.0}, "name": "19, Jan."}, {"data": {"CO": 1.8, "PM10": 220.0, "O3": 64.0, "SO2": 40.0, "NO2": 76.0, "AQI": 135.0, "PM25": 75.0}, "name": "20, Jan."}, {"data": {"CO": 2.2, "PM10": 159.0, "O3": 65.0, "SO2": 48.0, "NO2": 85.0, "AQI": 105.0, "PM25": 70.0}, "name": "21, Jan."}, {"data": {"CO": 2.2, "PM10": 128.0, "O3": 76.0, "SO2": 48.0, "NO2": 86.0, "AQI": 103.0, "PM25": 61.0}, "name": "22, Jan."}, {"data": {"CO": 2.8, "PM10": 160.0, "O3": 73.0, "SO2": 50.0, "NO2": 100.0, "AQI": 118.0, "PM25": 89.0}, "name": "23, Jan."}, {"data": {"CO": 3.2, "PM10": 178.0, "O3": 72.0, "SO2": 61.0, "NO2": 110.0, "AQI": 135.0, "PM25": 103.0}, "name": "24, Jan."}, {"data": {"CO": 2.6, "PM10": 604.0, "O3": 64.0, "SO2": 41.0, "NO2": 92.0, "AQI": 500.0, "PM25": 155.0}, "name": "25, Jan."}, {"data": {"CO": 0.8, "PM10": 1344.0, "O3": 76.0, "SO2": 16.0, "NO2": 36.0, "AQI": 500.0, "PM25": 212.0}, "name": "26, Jan."}, {"data": {"CO": 1.6, "PM10": 261.0, "O3": 70.0, "SO2": 31.0, "NO2": 61.0, "AQI": 156.0, "PM25": 69.0}, "name": "27, Jan."}, {"data": {"CO": 1.0, "PM10": 260.0, "O3": 79.0, "SO2": 28.0, "NO2": 36.0, "AQI": 155.0, "PM25": 61.0}, "name": "28, Jan."}, {"data": {"CO": 1.0, "PM10": 148.0, "O3": 84.0, "SO2": 20.0, "NO2": 34.0, "AQI": 99.0, "PM25": 38.0}, "name": "29, Jan."}, {"data": {"CO": 1.2, "PM10": 136.0, "O3": 85.0, "SO2": 30.0, "NO2": 38.0, "AQI": 93.0, "PM25": 40.0}, "name": "30, Jan."}, {"data": {"CO": 1.2, "PM10": 122.0, "O3": 80.0, "SO2": 28.0, "NO2": 46.0, "AQI": 86.0, "PM25": 43.0}, "name": "31, Jan."}]}, {"data": {"CO": 1.5821428571428566, "PM10": 146.21428571428572, "O3": 91.85714285714286, "SO2": 25.714285714285715, "NO2": 61.964285714285715, "AQI": 103.75, "PM25": 63.464285714285715}, "name": "Feb.", "children": [{"data": {"CO": 1.5, "PM10": 111.0, "O3": 65.0, "SO2": 32.0, "NO2": 54.0, "AQI": 81.0, "PM25": 51.0}, "name": "1, Feb."}, {"data": {"CO": 1.8, "PM10": 121.0, "O3": 82.0, "SO2": 22.0, "NO2": 58.0, "AQI": 94.0, "PM25": 70.0}, "name": "2, Feb."}, {"data": {"CO": 1.8, "PM10": 124.0, "O3": 73.0, "SO2": 30.0, "NO2": 62.0, "AQI": 95.0, "PM25": 71.0}, "name": "3, Feb."}, {"data": {"CO": 2.2, "PM10": 126.0, "O3": 74.0, "SO2": 32.0, "NO2": 84.0, "AQI": 102.0, "PM25": 66.0}, "name": "4, Feb."}, {"data": {"CO": 2.7, "PM10": 161.0, "O3": 84.0, "SO2": 41.0, "NO2": 102.0, "AQI": 124.0, "PM25": 94.0}, "name": "5, Feb."}, {"data": {"CO": 1.5, "PM10": 155.0, "O3": 62.0, "SO2": 34.0, "NO2": 44.0, "AQI": 103.0, "PM25": 66.0}, "name": "6, Feb."}, {"data": {"CO": 0.7, "PM10": 120.0, "O3": 78.0, "SO2": 14.0, "NO2": 24.0, "AQI": 85.0, "PM25": 32.0}, "name": "7, Feb."}, {"data": {"CO": 0.9, "PM10": 76.0, "O3": 76.0, "SO2": 14.0, "NO2": 37.0, "AQI": 63.0, "PM25": 39.0}, "name": "8, Feb."}, {"data": {"CO": 1.3, "PM10": 102.0, "O3": 101.0, "SO2": 17.0, "NO2": 54.0, "AQI": 88.0, "PM25": 65.0}, "name": "9, Feb."}, {"data": {"CO": 0.9, "PM10": 59.0, "O3": 78.0, "SO2": 26.0, "NO2": 43.0, "AQI": 55.0, "PM25": 32.0}, "name": "10, Feb."}, {"data": {"CO": 1.9, "PM10": 114.0, "O3": 92.0, "SO2": 30.0, "NO2": 78.0, "AQI": 98.0, "PM25": 66.0}, "name": "11, Feb."}, {"data": {"CO": 2.4, "PM10": 163.0, "O3": 87.0, "SO2": 30.0, "NO2": 100.0, "AQI": 134.0, "PM25": 102.0}, "name": "12, Feb."}, {"data": {"CO": 2.1, "PM10": 150.0, "O3": 121.0, "SO2": 35.0, "NO2": 85.0, "AQI": 118.0, "PM25": 89.0}, "name": "13, Feb."}, {"data": {"CO": 2.2, "PM10": 129.0, "O3": 89.0, "SO2": 29.0, "NO2": 89.0, "AQI": 105.0, "PM25": 70.0}, "name": "14, Feb."}, {"data": {"CO": 2.5, "PM10": 170.0, "O3": 98.0, "SO2": 30.0, "NO2": 85.0, "AQI": 110.0, "PM25": 73.0}, "name": "15, Feb."}, {"data": {"CO": 1.4, "PM10": 219.0, "O3": 83.0, "SO2": 24.0, "NO2": 50.0, "AQI": 135.0, "PM25": 55.0}, "name": "16, Feb."}, {"data": {"CO": 1.4, "PM10": 180.0, "O3": 95.0, "SO2": 22.0, "NO2": 61.0, "AQI": 115.0, "PM25": 56.0}, "name": "17, Feb."}, {"data": {"CO": 2.2, "PM10": 194.0, "O3": 108.0, "SO2": 34.0, "NO2": 88.0, "AQI": 122.0, "PM25": 77.0}, "name": "18, Feb."}, {"data": {"CO": 2.3, "PM10": 200.0, "O3": 91.0, "SO2": 36.0, "NO2": 88.0, "AQI": 125.0, "PM25": 84.0}, "name": "19, Feb."}, {"data": {"CO": 1.3, "PM10": 264.0, "O3": 84.0, "SO2": 22.0, "NO2": 48.0, "AQI": 157.0, "PM25": 65.0}, "name": "20, Feb."}, {"data": {"CO": 0.8, "PM10": 286.0, "O3": 74.0, "SO2": 22.0, "NO2": 32.0, "AQI": 168.0, "PM25": 76.0}, "name": "21, Feb."}, {"data": {"CO": 0.9, "PM10": 182.0, "O3": 82.0, "SO2": 23.0, "NO2": 39.0, "AQI": 116.0, "PM25": 56.0}, "name": "22, Feb."}, {"data": {"CO": 1.4, "PM10": 133.0, "O3": 113.0, "SO2": 16.0, "NO2": 59.0, "AQI": 92.0, "PM25": 60.0}, "name": "23, Feb."}, {"data": {"CO": 1.4, "PM10": 123.0, "O3": 112.0, "SO2": 16.0, "NO2": 58.0, "AQI": 92.0, "PM25": 68.0}, "name": "24, Feb."}, {"data": {"CO": 1.1, "PM10": 74.0, "O3": 103.0, "SO2": 20.0, "NO2": 50.0, "AQI": 63.0, "PM25": 39.0}, "name": "25, Feb."}, {"data": {"CO": 1.4, "PM10": 96.0, "O3": 123.0, "SO2": 26.0, "NO2": 62.0, "AQI": 78.0, "PM25": 52.0}, "name": "26, Feb."}, {"data": {"CO": 1.4, "PM10": 109.0, "O3": 140.0, "SO2": 27.0, "NO2": 61.0, "AQI": 85.0, "PM25": 63.0}, "name": "27, Feb."}, {"data": {"CO": 0.9, "PM10": 153.0, "O3": 104.0, "SO2": 16.0, "NO2": 40.0, "AQI": 102.0, "PM25": 40.0}, "name": "28, Feb."}]}, {"data": {"CO": 1.0806451612903227, "PM10": 114.93548387096774, "O3": 100.70967741935483, "SO2": 14.67741935483871, "NO2": 52.54838709677419, "AQI": 85.93548387096774, "PM25": 49.064516129032256}, "name": "Mar.", "children": [{"data": {"CO": 1.0, "PM10": 238.0, "O3": 101.0, "SO2": 12.0, "NO2": 55.0, "AQI": 144.0, "PM25": 51.0}, "name": "1, Mar."}, {"data": {"CO": 1.4, "PM10": 149.0, "O3": 110.0, "SO2": 26.0, "NO2": 65.0, "AQI": 100.0, "PM25": 46.0}, "name": "2, Mar."}, {"data": {"CO": 1.4, "PM10": 152.0, "O3": 118.0, "SO2": 24.0, "NO2": 70.0, "AQI": 101.0, "PM25": 49.0}, "name": "3, Mar."}, {"data": {"CO": 1.2, "PM10": 109.0, "O3": 79.0, "SO2": 22.0, "NO2": 60.0, "AQI": 80.0, "PM25": 47.0}, "name": "4, Mar."}, {"data": {"CO": 0.8, "PM10": 62.0, "O3": 110.0, "SO2": 12.0, "NO2": 44.0, "AQI": 59.0, "PM25": 32.0}, "name": "5, Mar."}, {"data": {"CO": 1.2, "PM10": 86.0, "O3": 108.0, "SO2": 17.0, "NO2": 54.0, "AQI": 68.0, "PM25": 42.0}, "name": "6, Mar."}, {"data": {"CO": 0.9, "PM10": 65.0, "O3": 88.0, "SO2": 17.0, "NO2": 51.0, "AQI": 64.0, "PM25": 32.0}, "name": "7, Mar."}, {"data": {"CO": 1.3, "PM10": 94.0, "O3": 122.0, "SO2": 21.0, "NO2": 70.0, "AQI": 88.0, "PM25": 46.0}, "name": "8, Mar."}, {"data": {"CO": 1.2, "PM10": 88.0, "O3": 76.0, "SO2": 26.0, "NO2": 56.0, "AQI": 70.0, "PM25": 44.0}, "name": "9, Mar."}, {"data": {"CO": 1.2, "PM10": 81.0, "O3": 77.0, "SO2": 15.0, "NO2": 48.0, "AQI": 66.0, "PM25": 46.0}, "name": "10, Mar."}, {"data": {"CO": 1.0, "PM10": 74.0, "O3": 86.0, "SO2": 17.0, "NO2": 44.0, "AQI": 67.0, "PM25": 48.0}, "name": "11, Mar."}, {"data": {"CO": 1.0, "PM10": 64.0, "O3": 64.0, "SO2": 12.0, "NO2": 38.0, "AQI": 62.0, "PM25": 44.0}, "name": "12, Mar."}, {"data": {"CO": 1.0, "PM10": 69.0, "O3": 71.0, "SO2": 16.0, "NO2": 41.0, "AQI": 65.0, "PM25": 47.0}, "name": "13, Mar."}, {"data": {"CO": 1.2, "PM10": 72.0, "O3": 85.0, "SO2": 11.0, "NO2": 54.0, "AQI": 72.0, "PM25": 52.0}, "name": "14, Mar."}, {"data": {"CO": 1.4, "PM10": 99.0, "O3": 100.0, "SO2": 12.0, "NO2": 66.0, "AQI": 87.0, "PM25": 64.0}, "name": "15, Mar."}, {"data": {"CO": 1.6, "PM10": 137.0, "O3": 134.0, "SO2": 16.0, "NO2": 68.0, "AQI": 112.0, "PM25": 84.0}, "name": "16, Mar."}, {"data": {"CO": 1.0, "PM10": 86.0, "O3": 87.0, "SO2": 11.0, "NO2": 44.0, "AQI": 68.0, "PM25": 47.0}, "name": "17, Mar."}, {"data": {"CO": 1.5, "PM10": 115.0, "O3": 77.0, "SO2": 14.0, "NO2": 64.0, "AQI": 87.0, "PM25": 64.0}, "name": "18, Mar."}, {"data": {"CO": 1.3, "PM10": 80.0, "O3": 116.0, "SO2": 8.0, "NO2": 49.0, "AQI": 70.0, "PM25": 51.0}, "name": "19, Mar."}, {"data": {"CO": 1.4, "PM10": 119.0, "O3": 114.0, "SO2": 14.0, "NO2": 61.0, "AQI": 85.0, "PM25": 52.0}, "name": "20, Mar."}, {"data": {"CO": 1.2, "PM10": 96.0, "O3": 104.0, "SO2": 12.0, "NO2": 57.0, "AQI": 73.0, "PM25": 44.0}, "name": "21, Mar."}, {"data": {"CO": 1.3, "PM10": 100.0, "O3": 90.0, "SO2": 12.0, "NO2": 60.0, "AQI": 75.0, "PM25": 52.0}, "name": "22, Mar."}, {"data": {"CO": 0.6, "PM10": 86.0, "O3": 90.0, "SO2": 8.0, "NO2": 36.0, "AQI": 68.0, "PM25": 42.0}, "name": "23, Mar."}, {"data": {"CO": 0.6, "PM10": 128.0, "O3": 98.0, "SO2": 11.0, "NO2": 38.0, "AQI": 89.0, "PM25": 48.0}, "name": "24, Mar."}, {"data": {"CO": 0.6, "PM10": 130.0, "O3": 110.0, "SO2": 8.0, "NO2": 29.0, "AQI": 90.0, "PM25": 35.0}, "name": "25, Mar."}, {"data": {"CO": 1.0, "PM10": 163.0, "O3": 138.0, "SO2": 14.0, "NO2": 66.0, "AQI": 107.0, "PM25": 46.0}, "name": "26, Mar."}, {"data": {"CO": 1.2, "PM10": 201.0, "O3": 142.0, "SO2": 18.0, "NO2": 64.0, "AQI": 126.0, "PM25": 63.0}, "name": "27, Mar."}, {"data": {"CO": 0.8, "PM10": 292.0, "O3": 93.0, "SO2": 11.0, "NO2": 50.0, "AQI": 171.0, "PM25": 84.0}, "name": "28, Mar."}, {"data": {"CO": 0.9, "PM10": 192.0, "O3": 100.0, "SO2": 16.0, "NO2": 50.0, "AQI": 121.0, "PM25": 59.0}, "name": "29, Mar."}, {"data": {"CO": 0.6, "PM10": 68.0, "O3": 113.0, "SO2": 9.0, "NO2": 36.0, "AQI": 61.0, "PM25": 30.0}, "name": "30, Mar."}, {"data": {"CO": 0.7, "PM10": 68.0, "O3": 121.0, "SO2": 13.0, "NO2": 41.0, "AQI": 68.0, "PM25": 30.0}, "name": "31, Mar."}]}]}, {"data": {"CO": 0.7417582417582422, "PM10": 82.47252747252747, "O3": 135.92307692307693, "SO2": 10.010989010989011, "NO2": 44.31868131868132, "AQI": 87.14285714285714, "PM25": 33.472527472527474}, "name": "Q2", "children": [{"data": {"CO": 0.72, "PM10": 149.46666666666667, "O3": 119.23333333333333, "SO2": 10.433333333333334, "NO2": 50.2, "AQI": 113.93333333333334, "PM25": 53.3}, "name": "Apr.", "children": [{"data": {"CO": 0.8, "PM10": 111.0, "O3": 120.0, "SO2": 13.0, "NO2": 65.0, "AQI": 82.0, "PM25": 39.0}, "name": "1, Apr."}, {"data": {"CO": 0.8, "PM10": 112.0, "O3": 103.0, "SO2": 12.0, "NO2": 58.0, "AQI": 81.0, "PM25": 44.0}, "name": "2, Apr."}, {"data": {"CO": 1.0, "PM10": 93.0, "O3": 78.0, "SO2": 8.0, "NO2": 57.0, "AQI": 73.0, "PM25": 53.0}, "name": "3, Apr."}, {"data": {"CO": 1.0, "PM10": 110.0, "O3": 149.0, "SO2": 10.0, "NO2": 56.0, "AQI": 91.0, "PM25": 66.0}, "name": "4, Apr."}, {"data": {"CO": 1.0, "PM10": 148.0, "O3": 146.0, "SO2": 14.0, "NO2": 76.0, "AQI": 99.0, "PM25": 61.0}, "name": "5, Apr."}, {"data": {"CO": 0.7, "PM10": 155.0, "O3": 117.0, "SO2": 8.0, "NO2": 46.0, "AQI": 103.0, "PM25": 54.0}, "name": "6, Apr."}, {"data": {"CO": 0.6, "PM10": 218.0, "O3": 84.0, "SO2": 12.0, "NO2": 35.0, "AQI": 134.0, "PM25": 70.0}, "name": "7, Apr."}, {"data": {"CO": 0.6, "PM10": 55.0, "O3": 70.0, "SO2": 4.0, "NO2": 29.0, "AQI": 53.0, "PM25": 36.0}, "name": "8, Apr."}, {"data": {"CO": 0.6, "PM10": 63.0, "O3": 65.0, "SO2": 6.0, "NO2": 38.0, "AQI": 64.0, "PM25": 46.0}, "name": "9, Apr."}, {"data": {"CO": 0.5, "PM10": 54.0, "O3": 71.0, "SO2": 7.0, "NO2": 37.0, "AQI": 59.0, "PM25": 42.0}, "name": "10, Apr."}, {"data": {"CO": 0.8, "PM10": 78.0, "O3": 117.0, "SO2": 8.0, "NO2": 55.0, "AQI": 69.0, "PM25": 42.0}, "name": "11, Apr."}, {"data": {"CO": 0.8, "PM10": 117.0, "O3": 118.0, "SO2": 10.0, "NO2": 49.0, "AQI": 84.0, "PM25": 47.0}, "name": "12, Apr."}, {"data": {"CO": 0.8, "PM10": 131.0, "O3": 142.0, "SO2": 14.0, "NO2": 63.0, "AQI": 91.0, "PM25": 52.0}, "name": "13, Apr."}, {"data": {"CO": 0.8, "PM10": 170.0, "O3": 136.0, "SO2": 15.0, "NO2": 56.0, "AQI": 110.0, "PM25": 53.0}, "name": "14, Apr."}, {"data": {"CO": 0.6, "PM10": 74.0, "O3": 95.0, "SO2": 6.0, "NO2": 42.0, "AQI": 62.0, "PM25": 38.0}, "name": "15, Apr."}, {"data": {"CO": 0.7, "PM10": 115.0, "O3": 103.0, "SO2": 10.0, "NO2": 48.0, "AQI": 83.0, "PM25": 49.0}, "name": "16, Apr."}, {"data": {"CO": 0.8, "PM10": 564.0, "O3": 138.0, "SO2": 13.0, "NO2": 52.0, "AQI": 464.0, "PM25": 132.0}, "name": "17, Apr."}, {"data": {"CO": 0.7, "PM10": 655.0, "O3": 113.0, "SO2": 9.0, "NO2": 48.0, "AQI": 500.0, "PM25": 158.0}, "name": "18, Apr."}, {"data": {"CO": 0.4, "PM10": 82.0, "O3": 97.0, "SO2": 6.0, "NO2": 27.0, "AQI": 66.0, "PM25": 34.0}, "name": "19, Apr."}, {"data": {"CO": 0.6, "PM10": 142.0, "O3": 112.0, "SO2": 10.0, "NO2": 44.0, "AQI": 96.0, "PM25": 50.0}, "name": "20, Apr."}, {"data": {"CO": 0.7, "PM10": 226.0, "O3": 132.0, "SO2": 10.0, "NO2": 57.0, "AQI": 138.0, "PM25": 60.0}, "name": "21, Apr."}, {"data": {"CO": 0.8, "PM10": 164.0, "O3": 146.0, "SO2": 13.0, "NO2": 61.0, "AQI": 107.0, "PM25": 46.0}, "name": "22, Apr."}, {"data": {"CO": 0.9, "PM10": 134.0, "O3": 163.0, "SO2": 16.0, "NO2": 69.0, "AQI": 103.0, "PM25": 43.0}, "name": "23, Apr."}, {"data": {"CO": 0.7, "PM10": 160.0, "O3": 137.0, "SO2": 13.0, "NO2": 58.0, "AQI": 105.0, "PM25": 45.0}, "name": "24, Apr."}, {"data": {"CO": 0.5, "PM10": 61.0, "O3": 125.0, "SO2": 6.0, "NO2": 25.0, "AQI": 71.0, "PM25": 32.0}, "name": "25, Apr."}, {"data": {"CO": 0.5, "PM10": 64.0, "O3": 96.0, "SO2": 6.0, "NO2": 40.0, "AQI": 57.0, "PM25": 32.0}, "name": "26, Apr."}, {"data": {"CO": 0.7, "PM10": 98.0, "O3": 152.0, "SO2": 8.0, "NO2": 56.0, "AQI": 94.0, "PM25": 40.0}, "name": "27, Apr."}, {"data": {"CO": 0.8, "PM10": 122.0, "O3": 151.0, "SO2": 16.0, "NO2": 62.0, "AQI": 93.0, "PM25": 45.0}, "name": "28, Apr."}, {"data": {"CO": 0.8, "PM10": 120.0, "O3": 167.0, "SO2": 19.0, "NO2": 63.0, "AQI": 107.0, "PM25": 46.0}, "name": "29, Apr."}, {"data": {"CO": 0.6, "PM10": 88.0, "O3": 134.0, "SO2": 11.0, "NO2": 34.0, "AQI": 79.0, "PM25": 44.0}, "name": "30, Apr."}]}, {"data": {"CO": 0.6419354838709675, "PM10": 166.96774193548387, "O3": 135.90322580645162, "SO2": 10.903225806451612, "NO2": 48.225806451612904, "AQI": 124.38709677419355, "PM25": 55.96774193548387}, "name": "May.", "children": [{"data": {"CO": 0.8, "PM10": 128.0, "O3": 184.0, "SO2": 15.0, "NO2": 60.0, "AQI": 122.0, "PM25": 46.0}, "name": "1, May."}, {"data": {"CO": 0.6, "PM10": 108.0, "O3": 101.0, "SO2": 6.0, "NO2": 32.0, "AQI": 79.0, "PM25": 55.0}, "name": "2, May."}, {"data": {"CO": 0.5, "PM10": 311.0, "O3": 106.0, "SO2": 6.0, "NO2": 34.0, "AQI": 181.0, "PM25": 75.0}, "name": "3, May."}, {"data": {"CO": 0.6, "PM10": 508.0, "O3": 133.0, "SO2": 10.0, "NO2": 42.0, "AQI": 408.0, "PM25": 98.0}, "name": "4, May."}, {"data": {"CO": 0.4, "PM10": 758.0, "O3": 98.0, "SO2": 8.0, "NO2": 36.0, "AQI": 500.0, "PM25": 203.0}, "name": "5, May."}, {"data": {"CO": 0.7, "PM10": 290.0, "O3": 126.0, "SO2": 12.0, "NO2": 53.0, "AQI": 170.0, "PM25": 92.0}, "name": "6, May."}, {"data": {"CO": 0.6, "PM10": 113.0, "O3": 119.0, "SO2": 6.0, "NO2": 39.0, "AQI": 82.0, "PM25": 52.0}, "name": "7, May."}, {"data": {"CO": 0.7, "PM10": 108.0, "O3": 162.0, "SO2": 13.0, "NO2": 55.0, "AQI": 102.0, "PM25": 46.0}, "name": "8, May."}, {"data": {"CO": 0.6, "PM10": 170.0, "O3": 140.0, "SO2": 12.0, "NO2": 50.0, "AQI": 110.0, "PM25": 54.0}, "name": "9, May."}, {"data": {"CO": 0.7, "PM10": 196.0, "O3": 92.0, "SO2": 12.0, "NO2": 66.0, "AQI": 123.0, "PM25": 66.0}, "name": "10, May."}, {"data": {"CO": 0.6, "PM10": 86.0, "O3": 129.0, "SO2": 10.0, "NO2": 47.0, "AQI": 75.0, "PM25": 34.0}, "name": "11, May."}, {"data": {"CO": 0.9, "PM10": 140.0, "O3": 162.0, "SO2": 14.0, "NO2": 64.0, "AQI": 102.0, "PM25": 44.0}, "name": "12, May."}, {"data": {"CO": 0.8, "PM10": 179.0, "O3": 128.0, "SO2": 21.0, "NO2": 70.0, "AQI": 115.0, "PM25": 55.0}, "name": "13, May."}, {"data": {"CO": 0.5, "PM10": 58.0, "O3": 136.0, "SO2": 5.0, "NO2": 28.0, "AQI": 80.0, "PM25": 30.0}, "name": "14, May."}, {"data": {"CO": 0.6, "PM10": 73.0, "O3": 122.0, "SO2": 11.0, "NO2": 45.0, "AQI": 69.0, "PM25": 32.0}, "name": "15, May."}, {"data": {"CO": 0.7, "PM10": 95.0, "O3": 130.0, "SO2": 12.0, "NO2": 52.0, "AQI": 75.0, "PM25": 38.0}, "name": "16, May."}, {"data": {"CO": 0.7, "PM10": 108.0, "O3": 140.0, "SO2": 15.0, "NO2": 59.0, "AQI": 84.0, "PM25": 45.0}, "name": "17, May."}, {"data": {"CO": 0.6, "PM10": 69.0, "O3": 136.0, "SO2": 12.0, "NO2": 46.0, "AQI": 80.0, "PM25": 34.0}, "name": "18, May."}, {"data": {"CO": 0.7, "PM10": 120.0, "O3": 178.0, "SO2": 13.0, "NO2": 60.0, "AQI": 117.0, "PM25": 43.0}, "name": "19, May."}, {"data": {"CO": 0.6, "PM10": 93.0, "O3": 138.0, "SO2": 8.0, "NO2": 38.0, "AQI": 82.0, "PM25": 42.0}, "name": "20, May."}, {"data": {"CO": 0.4, "PM10": 167.0, "O3": 114.0, "SO2": 11.0, "NO2": 26.0, "AQI": 109.0, "PM25": 55.0}, "name": "21, May."}, {"data": {"CO": 0.5, "PM10": 141.0, "O3": 106.0, "SO2": 5.0, "NO2": 27.0, "AQI": 96.0, "PM25": 61.0}, "name": "22, May."}, {"data": {"CO": 0.6, "PM10": 96.0, "O3": 112.0, "SO2": 8.0, "NO2": 37.0, "AQI": 73.0, "PM25": 40.0}, "name": "23, May."}, {"data": {"CO": 0.5, "PM10": 84.0, "O3": 130.0, "SO2": 12.0, "NO2": 36.0, "AQI": 75.0, "PM25": 40.0}, "name": "24, May."}, {"data": {"CO": 0.6, "PM10": 90.0, "O3": 121.0, "SO2": 10.0, "NO2": 46.0, "AQI": 70.0, "PM25": 39.0}, "name": "25, May."}, {"data": {"CO": 0.6, "PM10": 102.0, "O3": 161.0, "SO2": 8.0, "NO2": 58.0, "AQI": 101.0, "PM25": 42.0}, "name": "26, May."}, {"data": {"CO": 0.7, "PM10": 114.0, "O3": 171.0, "SO2": 10.0, "NO2": 64.0, "AQI": 110.0, "PM25": 40.0}, "name": "27, May."}, {"data": {"CO": 0.7, "PM10": 100.0, "O3": 164.0, "SO2": 11.0, "NO2": 55.0, "AQI": 104.0, "PM25": 38.0}, "name": "28, May."}, {"data": {"CO": 0.7, "PM10": 169.0, "O3": 168.0, "SO2": 11.0, "NO2": 48.0, "AQI": 110.0, "PM25": 62.0}, "name": "29, May."}, {"data": {"CO": 0.8, "PM10": 213.0, "O3": 184.0, "SO2": 15.0, "NO2": 64.0, "AQI": 132.0, "PM25": 66.0}, "name": "30, May."}, {"data": {"CO": 0.9, "PM10": 189.0, "O3": 122.0, "SO2": 16.0, "NO2": 58.0, "AQI": 120.0, "PM25": 68.0}, "name": "31, May."}]}, {"data": {"CO": 0.7766666666666668, "PM10": 86.53333333333333, "O3": 144.56666666666666, "SO2": 10.0, "NO2": 48.2, "AQI": 91.8, "PM25": 37.4}, "name": "Jun.", "children": [{"data": {"CO": 0.6, "PM10": 109.0, "O3": 162.0, "SO2": 7.0, "NO2": 46.0, "AQI": 102.0, "PM25": 47.0}, "name": "1, Jun."}, {"data": {"CO": 0.7, "PM10": 126.0, "O3": 118.0, "SO2": 9.0, "NO2": 54.0, "AQI": 88.0, "PM25": 50.0}, "name": "2, Jun."}, {"data": {"CO": 0.8, "PM10": 74.0, "O3": 124.0, "SO2": 9.0, "NO2": 40.0, "AQI": 70.0, "PM25": 49.0}, "name": "3, Jun."}, {"data": {"CO": 0.8, "PM10": 55.0, "O3": 98.0, "SO2": 10.0, "NO2": 37.0, "AQI": 59.0, "PM25": 42.0}, "name": "4, Jun."}, {"data": {"CO": 0.8, "PM10": 54.0, "O3": 152.0, "SO2": 7.0, "NO2": 49.0, "AQI": 94.0, "PM25": 33.0}, "name": "5, Jun."}, {"data": {"CO": 0.8, "PM10": 59.0, "O3": 139.0, "SO2": 8.0, "NO2": 45.0, "AQI": 83.0, "PM25": 33.0}, "name": "6, Jun."}, {"data": {"CO": 0.8, "PM10": 75.0, "O3": 159.0, "SO2": 13.0, "NO2": 43.0, "AQI": 100.0, "PM25": 36.0}, "name": "7, Jun."}, {"data": {"CO": 0.7, "PM10": 66.0, "O3": 158.0, "SO2": 11.0, "NO2": 46.0, "AQI": 99.0, "PM25": 34.0}, "name": "8, Jun."}, {"data": {"CO": 0.7, "PM10": 52.0, "O3": 122.0, "SO2": 7.0, "NO2": 36.0, "AQI": 69.0, "PM25": 30.0}, "name": "9, Jun."}, {"data": {"CO": 0.8, "PM10": 106.0, "O3": 147.0, "SO2": 10.0, "NO2": 52.0, "AQI": 90.0, "PM25": 46.0}, "name": "10, Jun."}, {"data": {"CO": 0.8, "PM10": 109.0, "O3": 142.0, "SO2": 8.0, "NO2": 52.0, "AQI": 85.0, "PM25": 38.0}, "name": "11, Jun."}, {"data": {"CO": 0.9, "PM10": 102.0, "O3": 147.0, "SO2": 12.0, "NO2": 57.0, "AQI": 90.0, "PM25": 38.0}, "name": "12, Jun."}, {"data": {"CO": 0.7, "PM10": 71.0, "O3": 113.0, "SO2": 6.0, "NO2": 45.0, "AQI": 61.0, "PM25": 31.0}, "name": "13, Jun."}, {"data": {"CO": 0.7, "PM10": 70.0, "O3": 82.0, "SO2": 8.0, "NO2": 39.0, "AQI": 60.0, "PM25": 34.0}, "name": "14, Jun."}, {"data": {"CO": 0.8, "PM10": 72.0, "O3": 88.0, "SO2": 13.0, "NO2": 40.0, "AQI": 61.0, "PM25": 38.0}, "name": "15, Jun."}, {"data": {"CO": 0.8, "PM10": 88.0, "O3": 188.0, "SO2": 12.0, "NO2": 60.0, "AQI": 126.0, "PM25": 40.0}, "name": "16, Jun."}, {"data": {"CO": 0.8, "PM10": 99.0, "O3": 174.0, "SO2": 12.0, "NO2": 59.0, "AQI": 113.0, "PM25": 42.0}, "name": "17, Jun."}, {"data": {"CO": 0.8, "PM10": 92.0, "O3": 160.0, "SO2": 11.0, "NO2": 54.0, "AQI": 100.0, "PM25": 41.0}, "name": "18, Jun."}, {"data": {"CO": 0.9, "PM10": 120.0, "O3": 136.0, "SO2": 11.0, "NO2": 62.0, "AQI": 85.0, "PM25": 44.0}, "name": "19, Jun."}, {"data": {"CO": 0.8, "PM10": 79.0, "O3": 149.0, "SO2": 9.0, "NO2": 47.0, "AQI": 91.0, "PM25": 35.0}, "name": "20, Jun."}, {"data": {"CO": 0.8, "PM10": 60.0, "O3": 128.0, "SO2": 6.0, "NO2": 43.0, "AQI": 74.0, "PM25": 29.0}, "name": "21, Jun."}, {"data": {"CO": 0.8, "PM10": 92.0, "O3": 181.0, "SO2": 16.0, "NO2": 49.0, "AQI": 120.0, "PM25": 36.0}, "name": "22, Jun."}, {"data": {"CO": 0.6, "PM10": 128.0, "O3": 104.0, "SO2": 10.0, "NO2": 32.0, "AQI": 89.0, "PM25": 38.0}, "name": "23, Jun."}, {"data": {"CO": 0.8, "PM10": 98.0, "O3": 153.0, "SO2": 14.0, "NO2": 55.0, "AQI": 95.0, "PM25": 34.0}, "name": "24, Jun."}, {"data": {"CO": 0.8, "PM10": 108.0, "O3": 176.0, "SO2": 12.0, "NO2": 58.0, "AQI": 115.0, "PM25": 36.0}, "name": "25, Jun."}, {"data": {"CO": 0.8, "PM10": 95.0, "O3": 184.0, "SO2": 12.0, "NO2": 56.0, "AQI": 122.0, "PM25": 30.0}, "name": "26, Jun."}, {"data": {"CO": 0.8, "PM10": 86.0, "O3": 160.0, "SO2": 9.0, "NO2": 46.0, "AQI": 100.0, "PM25": 34.0}, "name": "27, Jun."}, {"data": {"CO": 0.9, "PM10": 84.0, "O3": 155.0, "SO2": 11.0, "NO2": 40.0, "AQI": 96.0, "PM25": 38.0}, "name": "28, Jun."}, {"data": {"CO": 0.8, "PM10": 84.0, "O3": 172.0, "SO2": 9.0, "NO2": 53.0, "AQI": 111.0, "PM25": 36.0}, "name": "29, Jun."}, {"data": {"CO": 0.7, "PM10": 83.0, "O3": 166.0, "SO2": 8.0, "NO2": 51.0, "AQI": 106.0, "PM25": 30.0}, "name": "30, Jun."}]}]}, {"data": {"CO": 1.2560439560439562, "PM10": 112.95604395604396, "O3": 86.50549450549451, "SO2": 20.373626373626372, "NO2": 59.48351648351648, "AQI": 85.93406593406593, "PM25": 47.40659340659341}, "name": "Q3", "children": [{"data": {"CO": 0.703225806451613, "PM10": 85.12903225806451, "O3": 147.09677419354838, "SO2": 10.258064516129032, "NO2": 40.61290322580645, "AQI": 94.35483870967742, "PM25": 31.806451612903224}, "name": "Jul.", "children": [{"data": {"CO": 0.7, "PM10": 72.0, "O3": 172.0, "SO2": 7.0, "NO2": 45.0, "AQI": 111.0, "PM25": 28.0}, "name": "1, Jul."}, {"data": {"CO": 0.6, "PM10": 106.0, "O3": 130.0, "SO2": 8.0, "NO2": 33.0, "AQI": 78.0, "PM25": 32.0}, "name": "2, Jul."}, {"data": {"CO": 0.7, "PM10": 50.0, "O3": 143.0, "SO2": 10.0, "NO2": 34.0, "AQI": 86.0, "PM25": 22.0}, "name": "3, Jul."}, {"data": {"CO": 0.9, "PM10": 101.0, "O3": 150.0, "SO2": 14.0, "NO2": 58.0, "AQI": 92.0, "PM25": 37.0}, "name": "4, Jul."}, {"data": {"CO": 0.7, "PM10": 56.0, "O3": 91.0, "SO2": 8.0, "NO2": 42.0, "AQI": 53.0, "PM25": 26.0}, "name": "5, Jul."}, {"data": {"CO": 0.8, "PM10": 83.0, "O3": 164.0, "SO2": 18.0, "NO2": 55.0, "AQI": 104.0, "PM25": 35.0}, "name": "6, Jul."}, {"data": {"CO": 0.9, "PM10": 95.0, "O3": 168.0, "SO2": 19.0, "NO2": 66.0, "AQI": 108.0, "PM25": 36.0}, "name": "7, Jul."}, {"data": {"CO": 0.8, "PM10": 125.0, "O3": 123.0, "SO2": 19.0, "NO2": 62.0, "AQI": 88.0, "PM25": 41.0}, "name": "8, Jul."}, {"data": {"CO": 0.6, "PM10": 72.0, "O3": 133.0, "SO2": 10.0, "NO2": 36.0, "AQI": 78.0, "PM25": 25.0}, "name": "9, Jul."}, {"data": {"CO": 0.7, "PM10": 87.0, "O3": 146.0, "SO2": 8.0, "NO2": 50.0, "AQI": 89.0, "PM25": 29.0}, "name": "10, Jul."}, {"data": {"CO": 0.8, "PM10": 102.0, "O3": 188.0, "SO2": 8.0, "NO2": 57.0, "AQI": 126.0, "PM25": 32.0}, "name": "11, Jul."}, {"data": {"CO": 0.9, "PM10": 109.0, "O3": 179.0, "SO2": 18.0, "NO2": 64.0, "AQI": 118.0, "PM25": 35.0}, "name": "12, Jul."}, {"data": {"CO": 0.8, "PM10": 93.0, "O3": 197.0, "SO2": 7.0, "NO2": 42.0, "AQI": 134.0, "PM25": 41.0}, "name": "13, Jul."}, {"data": {"CO": 0.8, "PM10": 98.0, "O3": 171.0, "SO2": 10.0, "NO2": 48.0, "AQI": 110.0, "PM25": 34.0}, "name": "14, Jul."}, {"data": {"CO": 0.8, "PM10": 82.0, "O3": 171.0, "SO2": 8.0, "NO2": 44.0, "AQI": 110.0, "PM25": 29.0}, "name": "15, Jul."}, {"data": {"CO": 0.5, "PM10": 78.0, "O3": 165.0, "SO2": 6.0, "NO2": 40.0, "AQI": 105.0, "PM25": 30.0}, "name": "16, Jul."}, {"data": {"CO": 0.6, "PM10": 62.0, "O3": 158.0, "SO2": 6.0, "NO2": 34.0, "AQI": 99.0, "PM25": 28.0}, "name": "17, Jul."}, {"data": {"CO": 0.7, "PM10": 79.0, "O3": 161.0, "SO2": 10.0, "NO2": 45.0, "AQI": 101.0, "PM25": 33.0}, "name": "18, Jul."}, {"data": {"CO": 0.7, "PM10": 120.0, "O3": 160.0, "SO2": 9.0, "NO2": 44.0, "AQI": 100.0, "PM25": 40.0}, "name": "19, Jul."}, {"data": {"CO": 0.7, "PM10": 184.0, "O3": 120.0, "SO2": 9.0, "NO2": 22.0, "AQI": 117.0, "PM25": 64.0}, "name": "20, Jul."}, {"data": {"CO": 0.6, "PM10": 80.0, "O3": 137.0, "SO2": 8.0, "NO2": 30.0, "AQI": 81.0, "PM25": 28.0}, "name": "21, Jul."}, {"data": {"CO": 0.5, "PM10": 108.0, "O3": 107.0, "SO2": 10.0, "NO2": 18.0, "AQI": 79.0, "PM25": 37.0}, "name": "22, Jul."}, {"data": {"CO": 0.6, "PM10": 64.0, "O3": 96.0, "SO2": 16.0, "NO2": 20.0, "AQI": 57.0, "PM25": 22.0}, "name": "23, Jul."}, {"data": {"CO": 0.6, "PM10": 56.0, "O3": 116.0, "SO2": 13.0, "NO2": 20.0, "AQI": 64.0, "PM25": 22.0}, "name": "24, Jul."}, {"data": {"CO": 0.7, "PM10": 68.0, "O3": 160.0, "SO2": 7.0, "NO2": 31.0, "AQI": 100.0, "PM25": 36.0}, "name": "25, Jul."}, {"data": {"CO": 0.6, "PM10": 50.0, "O3": 76.0, "SO2": 9.0, "NO2": 23.0, "AQI": 50.0, "PM25": 28.0}, "name": "26, Jul."}, {"data": {"CO": 0.6, "PM10": 27.0, "O3": 114.0, "SO2": 5.0, "NO2": 25.0, "AQI": 62.0, "PM25": 14.0}, "name": "27, Jul."}, {"data": {"CO": 0.7, "PM10": 43.0, "O3": 139.0, "SO2": 7.0, "NO2": 31.0, "AQI": 83.0, "PM25": 22.0}, "name": "28, Jul."}, {"data": {"CO": 0.8, "PM10": 79.0, "O3": 162.0, "SO2": 12.0, "NO2": 48.0, "AQI": 102.0, "PM25": 32.0}, "name": "29, Jul."}, {"data": {"CO": 0.8, "PM10": 96.0, "O3": 195.0, "SO2": 12.0, "NO2": 53.0, "AQI": 132.0, "PM25": 37.0}, "name": "30, Jul."}, {"data": {"CO": 0.6, "PM10": 114.0, "O3": 168.0, "SO2": 7.0, "NO2": 39.0, "AQI": 108.0, "PM25": 31.0}, "name": "31, Jul."}]}, {"data": {"CO": 0.7225806451612904, "PM10": 73.2258064516129, "O3": 112.0, "SO2": 9.451612903225806, "NO2": 42.83870967741935, "AQI": 72.61290322580645, "PM25": 30.258064516129032}, "name": "Aug.", "children": [{"data": {"CO": 0.6, "PM10": 118.0, "O3": 100.0, "SO2": 9.0, "NO2": 26.0, "AQI": 84.0, "PM25": 40.0}, "name": "1, Aug."}, {"data": {"CO": 0.8, "PM10": 88.0, "O3": 189.0, "SO2": 11.0, "NO2": 49.0, "AQI": 127.0, "PM25": 40.0}, "name": "2, Aug."}, {"data": {"CO": 0.7, "PM10": 124.0, "O3": 136.0, "SO2": 17.0, "NO2": 50.0, "AQI": 87.0, "PM25": 34.0}, "name": "3, Aug."}, {"data": {"CO": 0.7, "PM10": 66.0, "O3": 180.0, "SO2": 5.0, "NO2": 34.0, "AQI": 119.0, "PM25": 28.0}, "name": "4, Aug."}, {"data": {"CO": 0.8, "PM10": 70.0, "O3": 126.0, "SO2": 8.0, "NO2": 45.0, "AQI": 72.0, "PM25": 27.0}, "name": "5, Aug."}, {"data": {"CO": 0.9, "PM10": 62.0, "O3": 92.0, "SO2": 7.0, "NO2": 42.0, "AQI": 56.0, "PM25": 26.0}, "name": "6, Aug."}, {"data": {"CO": 0.7, "PM10": 57.0, "O3": 122.0, "SO2": 10.0, "NO2": 36.0, "AQI": 69.0, "PM25": 25.0}, "name": "7, Aug."}, {"data": {"CO": 0.6, "PM10": 78.0, "O3": 120.0, "SO2": 9.0, "NO2": 49.0, "AQI": 67.0, "PM25": 28.0}, "name": "8, Aug."}, {"data": {"CO": 1.0, "PM10": 76.0, "O3": 133.0, "SO2": 10.0, "NO2": 48.0, "AQI": 78.0, "PM25": 24.0}, "name": "9, Aug."}, {"data": {"CO": 1.1, "PM10": 104.0, "O3": 166.0, "SO2": 20.0, "NO2": 53.0, "AQI": 106.0, "PM25": 33.0}, "name": "10, Aug."}, {"data": {"CO": 0.8, "PM10": 93.0, "O3": 146.0, "SO2": 12.0, "NO2": 50.0, "AQI": 89.0, "PM25": 28.0}, "name": "11, Aug."}, {"data": {"CO": 0.7, "PM10": 66.0, "O3": 120.0, "SO2": 14.0, "NO2": 33.0, "AQI": 67.0, "PM25": 24.0}, "name": "12, Aug."}, {"data": {"CO": 0.8, "PM10": 57.0, "O3": 142.0, "SO2": 7.0, "NO2": 38.0, "AQI": 85.0, "PM25": 27.0}, "name": "13, Aug."}, {"data": {"CO": 0.7, "PM10": 98.0, "O3": 150.0, "SO2": 12.0, "NO2": 55.0, "AQI": 92.0, "PM25": 31.0}, "name": "14, Aug."}, {"data": {"CO": 0.7, "PM10": 92.0, "O3": 143.0, "SO2": 9.0, "NO2": 54.0, "AQI": 86.0, "PM25": 29.0}, "name": "15, Aug."}, {"data": {"CO": 0.6, "PM10": 94.0, "O3": 128.0, "SO2": 10.0, "NO2": 50.0, "AQI": 74.0, "PM25": 28.0}, "name": "16, Aug."}, {"data": {"CO": 0.6, "PM10": 66.0, "O3": 101.0, "SO2": 7.0, "NO2": 39.0, "AQI": 58.0, "PM25": 23.0}, "name": "17, Aug."}, {"data": {"CO": 0.7, "PM10": 71.0, "O3": 116.0, "SO2": 8.0, "NO2": 42.0, "AQI": 64.0, "PM25": 26.0}, "name": "18, Aug."}, {"data": {"CO": 0.7, "PM10": 70.0, "O3": 86.0, "SO2": 8.0, "NO2": 32.0, "AQI": 60.0, "PM25": 25.0}, "name": "19, Aug."}, {"data": {"CO": 0.4, "PM10": 36.0, "O3": 76.0, "SO2": 5.0, "NO2": 27.0, "AQI": 38.0, "PM25": 20.0}, "name": "20, Aug."}, {"data": {"CO": 0.9, "PM10": 56.0, "O3": 60.0, "SO2": 6.0, "NO2": 42.0, "AQI": 53.0, "PM25": 32.0}, "name": "21, Aug."}, {"data": {"CO": 0.6, "PM10": 38.0, "O3": 83.0, "SO2": 6.0, "NO2": 34.0, "AQI": 43.0, "PM25": 20.0}, "name": "22, Aug."}, {"data": {"CO": 0.6, "PM10": 43.0, "O3": 66.0, "SO2": 8.0, "NO2": 39.0, "AQI": 49.0, "PM25": 28.0}, "name": "23, Aug."}, {"data": {"CO": 0.8, "PM10": 76.0, "O3": 54.0, "SO2": 12.0, "NO2": 52.0, "AQI": 65.0, "PM25": 44.0}, "name": "24, Aug."}, {"data": {"CO": 0.6, "PM10": 48.0, "O3": 33.0, "SO2": 9.0, "NO2": 41.0, "AQI": 52.0, "PM25": 34.0}, "name": "25, Aug."}, {"data": {"CO": 0.6, "PM10": 47.0, "O3": 87.0, "SO2": 6.0, "NO2": 34.0, "AQI": 47.0, "PM25": 26.0}, "name": "26, Aug."}, {"data": {"CO": 0.8, "PM10": 61.0, "O3": 64.0, "SO2": 10.0, "NO2": 46.0, "AQI": 58.0, "PM25": 34.0}, "name": "27, Aug."}, {"data": {"CO": 0.5, "PM10": 50.0, "O3": 77.0, "SO2": 8.0, "NO2": 44.0, "AQI": 55.0, "PM25": 31.0}, "name": "28, Aug."}, {"data": {"CO": 0.6, "PM10": 50.0, "O3": 80.0, "SO2": 8.0, "NO2": 38.0, "AQI": 50.0, "PM25": 26.0}, "name": "29, Aug."}, {"data": {"CO": 0.9, "PM10": 92.0, "O3": 104.0, "SO2": 10.0, "NO2": 50.0, "AQI": 71.0, "PM25": 40.0}, "name": "30, Aug."}, {"data": {"CO": 0.9, "PM10": 123.0, "O3": 192.0, "SO2": 12.0, "NO2": 56.0, "AQI": 130.0, "PM25": 57.0}, "name": "31, Aug."}]}, {"data": {"CO": 0.7333333333333335, "PM10": 96.16666666666667, "O3": 120.13333333333334, "SO2": 12.233333333333333, "NO2": 51.63333333333333, "AQI": 82.13333333333334, "PM25": 38.56666666666667}, "name": "Sep.", "children": [{"data": {"CO": 0.6, "PM10": 71.0, "O3": 119.0, "SO2": 8.0, "NO2": 42.0, "AQI": 66.0, "PM25": 29.0}, "name": "1, Sep."}, {"data": {"CO": 0.6, "PM10": 102.0, "O3": 152.0, "SO2": 11.0, "NO2": 59.0, "AQI": 94.0, "PM25": 40.0}, "name": "2, Sep."}, {"data": {"CO": 0.7, "PM10": 101.0, "O3": 135.0, "SO2": 11.0, "NO2": 54.0, "AQI": 80.0, "PM25": 33.0}, "name": "3, Sep."}, {"data": {"CO": 0.4, "PM10": 72.0, "O3": 100.0, "SO2": 10.0, "NO2": 36.0, "AQI": 61.0, "PM25": 27.0}, "name": "4, Sep."}, {"data": {"CO": 0.5, "PM10": 73.0, "O3": 82.0, "SO2": 7.0, "NO2": 46.0, "AQI": 62.0, "PM25": 29.0}, "name": "5, Sep."}, {"data": {"CO": 0.8, "PM10": 92.0, "O3": 131.0, "SO2": 16.0, "NO2": 52.0, "AQI": 76.0, "PM25": 34.0}, "name": "6, Sep."}, {"data": {"CO": 0.8, "PM10": 112.0, "O3": 166.0, "SO2": 15.0, "NO2": 61.0, "AQI": 106.0, "PM25": 44.0}, "name": "7, Sep."}, {"data": {"CO": 0.7, "PM10": 73.0, "O3": 160.0, "SO2": 9.0, "NO2": 57.0, "AQI": 100.0, "PM25": 30.0}, "name": "8, Sep."}, {"data": {"CO": 0.6, "PM10": 115.0, "O3": 79.0, "SO2": 16.0, "NO2": 59.0, "AQI": 83.0, "PM25": 37.0}, "name": "9, Sep."}, {"data": {"CO": 0.6, "PM10": 109.0, "O3": 138.0, "SO2": 13.0, "NO2": 58.0, "AQI": 82.0, "PM25": 36.0}, "name": "10, Sep."}, {"data": {"CO": 1.0, "PM10": 132.0, "O3": 182.0, "SO2": 22.0, "NO2": 68.0, "AQI": 120.0, "PM25": 44.0}, "name": "11, Sep."}, {"data": {"CO": 0.8, "PM10": 99.0, "O3": 100.0, "SO2": 8.0, "NO2": 39.0, "AQI": 75.0, "PM25": 34.0}, "name": "12, Sep."}, {"data": {"CO": 0.6, "PM10": 90.0, "O3": 92.0, "SO2": 7.0, "NO2": 40.0, "AQI": 70.0, "PM25": 35.0}, "name": "13, Sep."}, {"data": {"CO": 0.7, "PM10": 88.0, "O3": 87.0, "SO2": 11.0, "NO2": 48.0, "AQI": 69.0, "PM25": 42.0}, "name": "14, Sep."}, {"data": {"CO": 0.6, "PM10": 93.0, "O3": 136.0, "SO2": 10.0, "NO2": 46.0, "AQI": 80.0, "PM25": 44.0}, "name": "15, Sep."}, {"data": {"CO": 0.6, "PM10": 61.0, "O3": 146.0, "SO2": 8.0, "NO2": 40.0, "AQI": 89.0, "PM25": 28.0}, "name": "16, Sep."}, {"data": {"CO": 0.8, "PM10": 100.0, "O3": 162.0, "SO2": 16.0, "NO2": 49.0, "AQI": 102.0, "PM25": 41.0}, "name": "17, Sep."}, {"data": {"CO": 0.8, "PM10": 76.0, "O3": 53.0, "SO2": 12.0, "NO2": 51.0, "AQI": 64.0, "PM25": 40.0}, "name": "18, Sep."}, {"data": {"CO": 0.8, "PM10": 66.0, "O3": 88.0, "SO2": 8.0, "NO2": 53.0, "AQI": 67.0, "PM25": 40.0}, "name": "19, Sep."}, {"data": {"CO": 1.0, "PM10": 100.0, "O3": 148.0, "SO2": 12.0, "NO2": 63.0, "AQI": 90.0, "PM25": 47.0}, "name": "20, Sep."}, {"data": {"CO": 0.8, "PM10": 96.0, "O3": 114.0, "SO2": 11.0, "NO2": 56.0, "AQI": 73.0, "PM25": 39.0}, "name": "21, Sep."}, {"data": {"CO": 1.0, "PM10": 105.0, "O3": 121.0, "SO2": 24.0, "NO2": 58.0, "AQI": 78.0, "PM25": 44.0}, "name": "22, Sep."}, {"data": {"CO": 0.6, "PM10": 84.0, "O3": 70.0, "SO2": 10.0, "NO2": 50.0, "AQI": 67.0, "PM25": 35.0}, "name": "23, Sep."}, {"data": {"CO": 1.0, "PM10": 110.0, "O3": 103.0, "SO2": 12.0, "NO2": 56.0, "AQI": 80.0, "PM25": 45.0}, "name": "24, Sep."}, {"data": {"CO": 0.9, "PM10": 147.0, "O3": 121.0, "SO2": 14.0, "NO2": 48.0, "AQI": 99.0, "PM25": 58.0}, "name": "25, Sep."}, {"data": {"CO": 0.6, "PM10": 86.0, "O3": 76.0, "SO2": 6.0, "NO2": 35.0, "AQI": 68.0, "PM25": 42.0}, "name": "26, Sep."}, {"data": {"CO": 0.7, "PM10": 86.0, "O3": 154.0, "SO2": 10.0, "NO2": 46.0, "AQI": 95.0, "PM25": 40.0}, "name": "27, Sep."}, {"data": {"CO": 0.8, "PM10": 123.0, "O3": 166.0, "SO2": 18.0, "NO2": 66.0, "AQI": 106.0, "PM25": 42.0}, "name": "28, Sep."}, {"data": {"CO": 0.8, "PM10": 106.0, "O3": 105.0, "SO2": 17.0, "NO2": 60.0, "AQI": 78.0, "PM25": 36.0}, "name": "29, Sep."}, {"data": {"CO": 0.8, "PM10": 117.0, "O3": 118.0, "SO2": 15.0, "NO2": 53.0, "AQI": 84.0, "PM25": 42.0}, "name": "30, Sep."}]}]}, {"data": {"CO": 1.9989130434782612, "PM10": 184.3913043478261, "O3": 68.92391304347827, "SO2": 37.90217391304348, "NO2": 73.65217391304348, "AQI": 128.43478260869566, "PM25": 73.75}, "name": "Q4", "children": [{"data": {"CO": 1.1096774193548389, "PM10": 96.61290322580645, "O3": 73.48387096774194, "SO2": 13.612903225806452, "NO2": 51.096774193548384, "AQI": 75.19354838709677, "PM25": 44.41935483870968}, "name": "Oct.", "children": [{"data": {"CO": 0.7, "PM10": 160.0, "O3": 149.0, "SO2": 13.0, "NO2": 51.0, "AQI": 105.0, "PM25": 56.0}, "name": "1, Oct."}, {"data": {"CO": 0.4, "PM10": 168.0, "O3": 77.0, "SO2": 8.0, "NO2": 21.0, "AQI": 109.0, "PM25": 50.0}, "name": "2, Oct."}, {"data": {"CO": 0.6, "PM10": 63.0, "O3": 81.0, "SO2": 6.0, "NO2": 37.0, "AQI": 57.0, "PM25": 36.0}, "name": "3, Oct."}, {"data": {"CO": 0.8, "PM10": 76.0, "O3": 66.0, "SO2": 10.0, "NO2": 47.0, "AQI": 63.0, "PM25": 38.0}, "name": "4, Oct."}, {"data": {"CO": 0.8, "PM10": 78.0, "O3": 81.0, "SO2": 11.0, "NO2": 43.0, "AQI": 64.0, "PM25": 42.0}, "name": "5, Oct."}, {"data": {"CO": 0.8, "PM10": 61.0, "O3": 46.0, "SO2": 9.0, "NO2": 33.0, "AQI": 56.0, "PM25": 34.0}, "name": "6, Oct."}, {"data": {"CO": 0.8, "PM10": 68.0, "O3": 102.0, "SO2": 10.0, "NO2": 37.0, "AQI": 59.0, "PM25": 31.0}, "name": "7, Oct."}, {"data": {"CO": 0.5, "PM10": 69.0, "O3": 76.0, "SO2": 7.0, "NO2": 18.0, "AQI": 60.0, "PM25": 31.0}, "name": "8, Oct."}, {"data": {"CO": 0.4, "PM10": 31.0, "O3": 68.0, "SO2": 4.0, "NO2": 27.0, "AQI": 34.0, "PM25": 19.0}, "name": "9, Oct."}, {"data": {"CO": 0.8, "PM10": 65.0, "O3": 71.0, "SO2": 9.0, "NO2": 41.0, "AQI": 64.0, "PM25": 46.0}, "name": "10, Oct."}, {"data": {"CO": 1.1, "PM10": 86.0, "O3": 48.0, "SO2": 19.0, "NO2": 48.0, "AQI": 82.0, "PM25": 60.0}, "name": "11, Oct."}, {"data": {"CO": 1.1, "PM10": 98.0, "O3": 77.0, "SO2": 13.0, "NO2": 59.0, "AQI": 74.0, "PM25": 50.0}, "name": "12, Oct."}, {"data": {"CO": 1.3, "PM10": 102.0, "O3": 37.0, "SO2": 20.0, "NO2": 62.0, "AQI": 78.0, "PM25": 50.0}, "name": "13, Oct."}, {"data": {"CO": 1.2, "PM10": 90.0, "O3": 89.0, "SO2": 15.0, "NO2": 59.0, "AQI": 74.0, "PM25": 52.0}, "name": "14, Oct."}, {"data": {"CO": 1.8, "PM10": 142.0, "O3": 66.0, "SO2": 20.0, "NO2": 77.0, "AQI": 99.0, "PM25": 74.0}, "name": "15, Oct."}, {"data": {"CO": 1.0, "PM10": 77.0, "O3": 56.0, "SO2": 9.0, "NO2": 47.0, "AQI": 64.0, "PM25": 40.0}, "name": "16, Oct."}, {"data": {"CO": 0.9, "PM10": 41.0, "O3": 64.0, "SO2": 8.0, "NO2": 38.0, "AQI": 48.0, "PM25": 27.0}, "name": "17, Oct."}, {"data": {"CO": 1.1, "PM10": 74.0, "O3": 91.0, "SO2": 12.0, "NO2": 56.0, "AQI": 70.0, "PM25": 39.0}, "name": "18, Oct."}, {"data": {"CO": 1.3, "PM10": 104.0, "O3": 91.0, "SO2": 14.0, "NO2": 64.0, "AQI": 80.0, "PM25": 47.0}, "name": "19, Oct."}, {"data": {"CO": 1.2, "PM10": 100.0, "O3": 73.0, "SO2": 15.0, "NO2": 55.0, "AQI": 75.0, "PM25": 49.0}, "name": "20, Oct."}, {"data": {"CO": 1.0, "PM10": 111.0, "O3": 73.0, "SO2": 12.0, "NO2": 57.0, "AQI": 81.0, "PM25": 40.0}, "name": "21, Oct."}, {"data": {"CO": 1.8, "PM10": 136.0, "O3": 88.0, "SO2": 23.0, "NO2": 70.0, "AQI": 93.0, "PM25": 52.0}, "name": "22, Oct."}, {"data": {"CO": 1.6, "PM10": 104.0, "O3": 68.0, "SO2": 13.0, "NO2": 56.0, "AQI": 77.0, "PM25": 41.0}, "name": "23, Oct."}, {"data": {"CO": 1.2, "PM10": 76.0, "O3": 24.0, "SO2": 14.0, "NO2": 52.0, "AQI": 65.0, "PM25": 40.0}, "name": "24, Oct."}, {"data": {"CO": 1.2, "PM10": 73.0, "O3": 54.0, "SO2": 14.0, "NO2": 53.0, "AQI": 67.0, "PM25": 41.0}, "name": "25, Oct."}, {"data": {"CO": 1.7, "PM10": 123.0, "O3": 107.0, "SO2": 18.0, "NO2": 77.0, "AQI": 97.0, "PM25": 56.0}, "name": "26, Oct."}, {"data": {"CO": 1.6, "PM10": 136.0, "O3": 104.0, "SO2": 19.0, "NO2": 60.0, "AQI": 93.0, "PM25": 56.0}, "name": "27, Oct."}, {"data": {"CO": 0.7, "PM10": 82.0, "O3": 77.0, "SO2": 13.0, "NO2": 40.0, "AQI": 66.0, "PM25": 26.0}, "name": "28, Oct."}, {"data": {"CO": 1.0, "PM10": 114.0, "O3": 67.0, "SO2": 16.0, "NO2": 50.0, "AQI": 82.0, "PM25": 42.0}, "name": "29, Oct."}, {"data": {"CO": 2.0, "PM10": 141.0, "O3": 54.0, "SO2": 20.0, "NO2": 70.0, "AQI": 96.0, "PM25": 54.0}, "name": "30, Oct."}, {"data": {"CO": 2.0, "PM10": 146.0, "O3": 53.0, "SO2": 28.0, "NO2": 79.0, "AQI": 99.0, "PM25": 58.0}, "name": "31, Oct."}]}, {"data": {"CO": 1.93, "PM10": 146.63333333333333, "O3": 66.33333333333333, "SO2": 35.5, "NO2": 76.0, "AQI": 100.83333333333333, "PM25": 59.333333333333336}, "name": "Nov.", "children": [{"data": {"CO": 2.4, "PM10": 163.0, "O3": 95.0, "SO2": 32.0, "NO2": 92.0, "AQI": 107.0, "PM25": 68.0}, "name": "1, Nov."}, {"data": {"CO": 2.2, "PM10": 156.0, "O3": 85.0, "SO2": 32.0, "NO2": 86.0, "AQI": 103.0, "PM25": 62.0}, "name": "2, Nov."}, {"data": {"CO": 2.3, "PM10": 203.0, "O3": 76.0, "SO2": 36.0, "NO2": 83.0, "AQI": 127.0, "PM25": 64.0}, "name": "3, Nov."}, {"data": {"CO": 2.5, "PM10": 198.0, "O3": 72.0, "SO2": 42.0, "NO2": 88.0, "AQI": 124.0, "PM25": 74.0}, "name": "4, Nov."}, {"data": {"CO": 2.4, "PM10": 176.0, "O3": 94.0, "SO2": 30.0, "NO2": 94.0, "AQI": 113.0, "PM25": 81.0}, "name": "5, Nov."}, {"data": {"CO": 1.6, "PM10": 133.0, "O3": 82.0, "SO2": 26.0, "NO2": 62.0, "AQI": 92.0, "PM25": 55.0}, "name": "6, Nov."}, {"data": {"CO": 1.6, "PM10": 122.0, "O3": 94.0, "SO2": 29.0, "NO2": 81.0, "AQI": 101.0, "PM25": 55.0}, "name": "7, Nov."}, {"data": {"CO": 2.4, "PM10": 166.0, "O3": 57.0, "SO2": 37.0, "NO2": 92.0, "AQI": 108.0, "PM25": 68.0}, "name": "8, Nov."}, {"data": {"CO": 0.8, "PM10": 167.0, "O3": 65.0, "SO2": 18.0, "NO2": 48.0, "AQI": 109.0, "PM25": 45.0}, "name": "9, Nov."}, {"data": {"CO": 1.3, "PM10": 137.0, "O3": 68.0, "SO2": 20.0, "NO2": 54.0, "AQI": 94.0, "PM25": 44.0}, "name": "10, Nov."}, {"data": {"CO": 2.0, "PM10": 148.0, "O3": 62.0, "SO2": 29.0, "NO2": 66.0, "AQI": 99.0, "PM25": 65.0}, "name": "11, Nov."}, {"data": {"CO": 1.2, "PM10": 98.0, "O3": 86.0, "SO2": 21.0, "NO2": 50.0, "AQI": 74.0, "PM25": 38.0}, "name": "12, Nov."}, {"data": {"CO": 1.3, "PM10": 101.0, "O3": 92.0, "SO2": 25.0, "NO2": 61.0, "AQI": 77.0, "PM25": 40.0}, "name": "13, Nov."}, {"data": {"CO": 1.5, "PM10": 120.0, "O3": 77.0, "SO2": 26.0, "NO2": 76.0, "AQI": 95.0, "PM25": 49.0}, "name": "14, Nov."}, {"data": {"CO": 2.3, "PM10": 162.0, "O3": 43.0, "SO2": 35.0, "NO2": 84.0, "AQI": 106.0, "PM25": 67.0}, "name": "15, Nov."}, {"data": {"CO": 2.6, "PM10": 192.0, "O3": 56.0, "SO2": 39.0, "NO2": 91.0, "AQI": 121.0, "PM25": 90.0}, "name": "16, Nov."}, {"data": {"CO": 1.4, "PM10": 119.0, "O3": 51.0, "SO2": 30.0, "NO2": 52.0, "AQI": 85.0, "PM25": 57.0}, "name": "17, Nov."}, {"data": {"CO": 1.4, "PM10": 110.0, "O3": 30.0, "SO2": 42.0, "NO2": 59.0, "AQI": 80.0, "PM25": 46.0}, "name": "18, Nov."}, {"data": {"CO": 1.0, "PM10": 100.0, "O3": 72.0, "SO2": 41.0, "NO2": 43.0, "AQI": 75.0, "PM25": 37.0}, "name": "19, Nov."}, {"data": {"CO": 1.6, "PM10": 132.0, "O3": 40.0, "SO2": 33.0, "NO2": 76.0, "AQI": 95.0, "PM25": 47.0}, "name": "20, Nov."}, {"data": {"CO": 1.4, "PM10": 96.0, "O3": 74.0, "SO2": 34.0, "NO2": 51.0, "AQI": 73.0, "PM25": 37.0}, "name": "21, Nov."}, {"data": {"CO": 1.3, "PM10": 107.0, "O3": 68.0, "SO2": 30.0, "NO2": 74.0, "AQI": 93.0, "PM25": 40.0}, "name": "22, Nov."}, {"data": {"CO": 1.8, "PM10": 134.0, "O3": 69.0, "SO2": 42.0, "NO2": 88.0, "AQI": 104.0, "PM25": 50.0}, "name": "23, Nov."}, {"data": {"CO": 2.7, "PM10": 172.0, "O3": 46.0, "SO2": 43.0, "NO2": 90.0, "AQI": 111.0, "PM25": 71.0}, "name": "24, Nov."}, {"data": {"CO": 3.0, "PM10": 182.0, "O3": 49.0, "SO2": 57.0, "NO2": 89.0, "AQI": 116.0, "PM25": 78.0}, "name": "25, Nov."}, {"data": {"CO": 3.3, "PM10": 206.0, "O3": 67.0, "SO2": 56.0, "NO2": 110.0, "AQI": 128.0, "PM25": 95.0}, "name": "26, Nov."}, {"data": {"CO": 2.7, "PM10": 182.0, "O3": 44.0, "SO2": 50.0, "NO2": 93.0, "AQI": 116.0, "PM25": 87.0}, "name": "27, Nov."}, {"data": {"CO": 1.9, "PM10": 142.0, "O3": 47.0, "SO2": 43.0, "NO2": 77.0, "AQI": 97.0, "PM25": 61.0}, "name": "28, Nov."}, {"data": {"CO": 1.9, "PM10": 138.0, "O3": 60.0, "SO2": 45.0, "NO2": 76.0, "AQI": 95.0, "PM25": 55.0}, "name": "29, Nov."}, {"data": {"CO": 2.1, "PM10": 137.0, "O3": 69.0, "SO2": 42.0, "NO2": 94.0, "AQI": 107.0, "PM25": 54.0}, "name": "30, Nov."}]}, {"data": {"CO": 2.6032258064516136, "PM10": 207.16129032258064, "O3": 53.935483870967744, "SO2": 52.225806451612904, "NO2": 90.12903225806451, "AQI": 147.32258064516128, "PM25": 82.83870967741936}, "name": "Dec.", "children": [{"data": {"CO": 2.8, "PM10": 183.0, "O3": 61.0, "SO2": 56.0, "NO2": 110.0, "AQI": 117.0, "PM25": 86.0}, "name": "1, Dec."}, {"data": {"CO": 3.0, "PM10": 206.0, "O3": 54.0, "SO2": 58.0, "NO2": 116.0, "AQI": 143.0, "PM25": 109.0}, "name": "2, Dec."}, {"data": {"CO": 2.3, "PM10": 159.0, "O3": 63.0, "SO2": 49.0, "NO2": 91.0, "AQI": 110.0, "PM25": 83.0}, "name": "3, Dec."}, {"data": {"CO": 1.6, "PM10": 100.0, "O3": 66.0, "SO2": 37.0, "NO2": 76.0, "AQI": 95.0, "PM25": 44.0}, "name": "4, Dec."}, {"data": {"CO": 2.0, "PM10": 111.0, "O3": 49.0, "SO2": 35.0, "NO2": 82.0, "AQI": 101.0, "PM25": 46.0}, "name": "5, Dec."}, {"data": {"CO": 2.1, "PM10": 125.0, "O3": 47.0, "SO2": 46.0, "NO2": 72.0, "AQI": 90.0, "PM25": 59.0}, "name": "6, Dec."}, {"data": {"CO": 1.6, "PM10": 96.0, "O3": 59.0, "SO2": 42.0, "NO2": 64.0, "AQI": 80.0, "PM25": 43.0}, "name": "7, Dec."}, {"data": {"CO": 2.1, "PM10": 106.0, "O3": 36.0, "SO2": 50.0, "NO2": 75.0, "AQI": 94.0, "PM25": 48.0}, "name": "8, Dec."}, {"data": {"CO": 2.3, "PM10": 148.0, "O3": 55.0, "SO2": 57.0, "NO2": 77.0, "AQI": 99.0, "PM25": 62.0}, "name": "9, Dec."}, {"data": {"CO": 2.4, "PM10": 154.0, "O3": 63.0, "SO2": 47.0, "NO2": 95.0, "AQI": 108.0, "PM25": 66.0}, "name": "10, Dec."}, {"data": {"CO": 3.1, "PM10": 182.0, "O3": 52.0, "SO2": 58.0, "NO2": 100.0, "AQI": 117.0, "PM25": 88.0}, "name": "11, Dec."}, {"data": {"CO": 3.0, "PM10": 174.0, "O3": 49.0, "SO2": 58.0, "NO2": 94.0, "AQI": 112.0, "PM25": 80.0}, "name": "12, Dec."}, {"data": {"CO": 2.4, "PM10": 178.0, "O3": 61.0, "SO2": 72.0, "NO2": 86.0, "AQI": 120.0, "PM25": 91.0}, "name": "13, Dec."}, {"data": {"CO": 1.3, "PM10": 125.0, "O3": 42.0, "SO2": 34.0, "NO2": 60.0, "AQI": 88.0, "PM25": 53.0}, "name": "14, Dec."}, {"data": {"CO": 0.9, "PM10": 85.0, "O3": 76.0, "SO2": 31.0, "NO2": 42.0, "AQI": 68.0, "PM25": 36.0}, "name": "15, Dec."}, {"data": {"CO": 1.2, "PM10": 73.0, "O3": 58.0, "SO2": 27.0, "NO2": 54.0, "AQI": 68.0, "PM25": 36.0}, "name": "16, Dec."}, {"data": {"CO": 2.7, "PM10": 139.0, "O3": 46.0, "SO2": 54.0, "NO2": 86.0, "AQI": 103.0, "PM25": 72.0}, "name": "17, Dec."}, {"data": {"CO": 2.6, "PM10": 131.0, "O3": 35.0, "SO2": 61.0, "NO2": 83.0, "AQI": 102.0, "PM25": 66.0}, "name": "18, Dec."}, {"data": {"CO": 3.4, "PM10": 166.0, "O3": 62.0, "SO2": 72.0, "NO2": 104.0, "AQI": 120.0, "PM25": 91.0}, "name": "19, Dec."}, {"data": {"CO": 4.0, "PM10": 200.0, "O3": 45.0, "SO2": 73.0, "NO2": 118.0, "AQI": 145.0, "PM25": 111.0}, "name": "20, Dec."}, {"data": {"CO": 4.5, "PM10": 233.0, "O3": 65.0, "SO2": 72.0, "NO2": 136.0, "AQI": 186.0, "PM25": 140.0}, "name": "21, Dec."}, {"data": {"CO": 3.8, "PM10": 204.0, "O3": 47.0, "SO2": 77.0, "NO2": 124.0, "AQI": 155.0, "PM25": 118.0}, "name": "22, Dec."}, {"data": {"CO": 1.9, "PM10": 141.0, "O3": 64.0, "SO2": 36.0, "NO2": 72.0, "AQI": 96.0, "PM25": 51.0}, "name": "23, Dec."}, {"data": {"CO": 2.9, "PM10": 188.0, "O3": 50.0, "SO2": 58.0, "NO2": 97.0, "AQI": 119.0, "PM25": 71.0}, "name": "24, Dec."}, {"data": {"CO": 3.1, "PM10": 174.0, "O3": 57.0, "SO2": 64.0, "NO2": 103.0, "AQI": 112.0, "PM25": 82.0}, "name": "25, Dec."}, {"data": {"CO": 4.2, "PM10": 192.0, "O3": 44.0, "SO2": 80.0, "NO2": 135.0, "AQI": 129.0, "PM25": 98.0}, "name": "26, Dec."}, {"data": {"CO": 4.7, "PM10": 234.0, "O3": 61.0, "SO2": 70.0, "NO2": 146.0, "AQI": 176.0, "PM25": 133.0}, "name": "27, Dec."}, {"data": {"CO": 2.7, "PM10": 733.0, "O3": 52.0, "SO2": 52.0, "NO2": 87.0, "AQI": 500.0, "PM25": 157.0}, "name": "28, Dec."}, {"data": {"CO": 1.0, "PM10": 714.0, "O3": 56.0, "SO2": 15.0, "NO2": 49.0, "AQI": 500.0, "PM25": 124.0}, "name": "29, Dec."}, {"data": {"CO": 2.2, "PM10": 439.0, "O3": 44.0, "SO2": 26.0, "NO2": 72.0, "AQI": 324.0, "PM25": 112.0}, "name": "30, Dec."}, {"data": {"CO": 2.9, "PM10": 329.0, "O3": 53.0, "SO2": 52.0, "NO2": 88.0, "AQI": 190.0, "PM25": 112.0}, "name": "31, Dec."}]}]}]}